README.md
setup.py
archer_nlp/__init__.py
archer_nlp/common_utils.py
archer_nlp/crawler_util.py
archer_nlp/cut_utils.py
archer_nlp/mongo_util.py
archer_nlp/sql_util.py
archer_nlp/thread_util.py
archer_nlp.egg-info/PKG-INFO
archer_nlp.egg-info/SOURCES.txt
archer_nlp.egg-info/dependency_links.txt
archer_nlp.egg-info/requires.txt
archer_nlp.egg-info/top_level.txt