Metadata-Version: 2.1
Name: archer-nlp
Version: 0.1.29
Summary: archer nlp
Home-page: https://github.com/beybin/archer_nlp
Author: beybin
Author-email: 1092386160@qq.com
